landscape_api/__init__.py
landscape_api/__main__.py
landscape_api/base.py
landscape_api/schemas.json
landscape_api_py3-0.9.0.dist-info/AUTHORS.rst
landscape_api_py3-0.9.0.dist-info/LICENSE
landscape_api_py3-0.9.0.dist-info/METADATA
landscape_api_py3-0.9.0.dist-info/WHEEL
landscape_api_py3-0.9.0.dist-info/entry_points.txt
landscape_api_py3-0.9.0.dist-info/top_level.txt
landscape_api_py3-0.9.0.dist-info/RECORD
