Metadata-Version: 2.1
Name: landscape-api-py3
Version: 0.9.0
Summary: Client for the Landscape API (Python 3)
Home-page: https://github.com/jurya/landscape_api_py3
Author: Jiří Altman
Author-email: jiri.altman@konicaminolta.cz
License: MIT license
Keywords: landscape_api_py3
Classifier: Development Status :: 2 - Pre-Alpha
Classifier: Intended Audience :: Developers
Classifier: License :: OSI Approved :: MIT License
Classifier: Natural Language :: English
Classifier: Programming Language :: Python :: 3.5
Classifier: Programming Language :: Python :: 3.6
Classifier: Programming Language :: Python :: 3.7
Classifier: Programming Language :: Python :: 3.8
Requires-Python: >=3.5
License-File: LICENSE
License-File: AUTHORS.rst
Requires-Dist: requests
